[
  {
    "id": "member1",
    "name": "John Doe",
    "phone": "9876543210",
    "email": "john.doe@example.com",
    "avatarUrl": null,
    "membershipType": "monthly",
    "startDate": "2024-12-01T00:00:00.000Z",
    "endDate": "2025-01-01T00:00:00.000Z",
    "isActive": true,
    "lastPaymentDate": "2024-12-01T00:00:00.000Z",
    "nextPaymentDate": "2025-01-01T00:00:00.000Z",
    "notes": "Regular member",
    "createdAt": "2024-11-01T00:00:00.000Z",
    "updatedAt": "2024-12-01T00:00:00.000Z"
  },
  {
    "id": "member2",
    "name": "Jane Smith",
    "phone": "9876543211",
    "email": "jane.smith@example.com",
    "avatarUrl": null,
    "membershipType": "quarterly",
    "startDate": "2024-11-01T00:00:00.000Z",
    "endDate": "2025-02-01T00:00:00.000Z",
    "isActive": true,
    "lastPaymentDate": "2024-11-01T00:00:00.000Z",
    "nextPaymentDate": "2025-02-01T00:00:00.000Z",
    "notes": null,
    "createdAt": "2024-10-01T00:00:00.000Z",
    "updatedAt": "2024-11-01T00:00:00.000Z"
  },
  {
    "id": "member3",
    "name": "Mike Johnson",
    "phone": "9876543212",
    "email": "mike.johnson@example.com",
    "avatarUrl": null,
    "membershipType": "yearly",
    "startDate": "2024-01-01T00:00:00.000Z",
    "endDate": "2025-01-01T00:00:00.000Z",
    "isActive": true,
    "lastPaymentDate": "2024-01-01T00:00:00.000Z",
    "nextPaymentDate": "2025-01-01T00:00:00.000Z",
    "notes": "Premium member",
    "createdAt": "2023-12-01T00:00:00.000Z",
    "updatedAt": "2024-01-01T00:00:00.000Z"
  },
  {
    "id": "member4",
    "name": "Sarah Williams",
    "phone": "9876543213",
    "email": "sarah.williams@example.com",
    "avatarUrl": null,
    "membershipType": "monthly",
    "startDate": "2024-11-15T00:00:00.000Z",
    "endDate": "2024-12-15T00:00:00.000Z",
    "isActive": false,
    "lastPaymentDate": "2024-11-15T00:00:00.000Z",
    "nextPaymentDate": null,
    "notes": "Needs renewal",
    "createdAt": "2024-10-15T00:00:00.000Z",
    "updatedAt": "2024-11-15T00:00:00.000Z"
  },
  {
    "id": "member5",
    "name": "David Brown",
    "phone": "9876543214",
    "email": "david.brown@example.com",
    "avatarUrl": null,
    "membershipType": "monthly",
    "startDate": "2024-12-10T00:00:00.000Z",
    "endDate": "2025-01-10T00:00:00.000Z",
    "isActive": true,
    "lastPaymentDate": "2024-12-10T00:00:00.000Z",
    "nextPaymentDate": "2025-01-10T00:00:00.000Z",
    "notes": null,
    "createdAt": "2024-11-10T00:00:00.000Z",
    "updatedAt": "2024-12-10T00:00:00.000Z"
  },
  {
    "id": "member6",
    "name": "Emily Davis",
    "phone": "9876543215",
    "email": "emily.davis@example.com",
    "avatarUrl": null,
    "membershipType": "monthly",
    "startDate": "2024-12-10T00:00:00.000Z",
    "endDate": "2024-12-20T00:00:00.000Z",
    "isActive": true,
    "lastPaymentDate": "2024-12-10T00:00:00.000Z",
    "nextPaymentDate": "2024-12-20T00:00:00.000Z",
    "notes": "Pending renewal - expires soon",
    "createdAt": "2024-11-10T00:00:00.000Z",
    "updatedAt": "2024-12-10T00:00:00.000Z"
  },
  {
    "id": "member7",
    "name": "Robert Wilson",
    "phone": "9876543216",
    "email": "robert.wilson@example.com",
    "avatarUrl": null,
    "membershipType": "monthly",
    "startDate": "2024-12-05T00:00:00.000Z",
    "endDate": "2024-12-18T00:00:00.000Z",
    "isActive": true,
    "lastPaymentDate": "2024-12-05T00:00:00.000Z",
    "nextPaymentDate": "2024-12-18T00:00:00.000Z",
    "notes": "Renewal due in 2 days",
    "createdAt": "2024-11-05T00:00:00.000Z",
    "updatedAt": "2024-12-05T00:00:00.000Z"
  },
  {
    "id": "member8",
    "name": "Lisa Anderson",
    "phone": "9876543217",
    "email": "lisa.anderson@example.com",
    "avatarUrl": null,
    "membershipType": "quarterly",
    "startDate": "2024-12-01T00:00:00.000Z",
    "endDate": "2024-12-22T00:00:00.000Z",
    "isActive": true,
    "lastPaymentDate": "2024-12-01T00:00:00.000Z",
    "nextPaymentDate": "2024-12-22T00:00:00.000Z",
    "notes": "Quarterly membership expiring",
    "createdAt": "2024-09-01T00:00:00.000Z",
    "updatedAt": "2024-12-01T00:00:00.000Z"
  },
  {
    "id": "member9",
    "name": "James Taylor",
    "phone": "9876543218",
    "email": "james.taylor@example.com",
    "avatarUrl": null,
    "membershipType": "monthly",
    "startDate": "2024-11-01T00:00:00.000Z",
    "endDate": "2024-12-01T00:00:00.000Z",
    "isActive": false,
    "lastPaymentDate": "2024-11-01T00:00:00.000Z",
    "nextPaymentDate": null,
    "notes": "Expired membership",
    "createdAt": "2024-10-01T00:00:00.000Z",
    "updatedAt": "2024-11-01T00:00:00.000Z"
  },
  {
    "id": "member10",
    "name": "Maria Garcia",
    "phone": "9876543219",
    "email": "maria.garcia@example.com",
    "avatarUrl": null,
    "membershipType": "monthly",
    "startDate": "2024-10-15T00:00:00.000Z",
    "endDate": "2024-11-15T00:00:00.000Z",
    "isActive": false,
    "lastPaymentDate": "2024-10-15T00:00:00.000Z",
    "nextPaymentDate": null,
    "notes": "Expired - needs renewal",
    "createdAt": "2024-09-15T00:00:00.000Z",
    "updatedAt": "2024-10-15T00:00:00.000Z"
  },
  {
    "id": "member11",
    "name": "William Martinez",
    "phone": "9876543220",
    "email": "william.martinez@example.com",
    "avatarUrl": null,
    "membershipType": "yearly",
    "startDate": "2023-12-01T00:00:00.000Z",
    "endDate": "2024-12-01T00:00:00.000Z",
    "isActive": false,
    "lastPaymentDate": "2023-12-01T00:00:00.000Z",
    "nextPaymentDate": null,
    "notes": "Yearly membership expired",
    "createdAt": "2023-11-01T00:00:00.000Z",
    "updatedAt": "2023-12-01T00:00:00.000Z"
  },
  {
    "id": "member12",
    "name": "Jennifer Lee",
    "phone": "9876543221",
    "email": "jennifer.lee@example.com",
    "avatarUrl": null,
    "membershipType": "monthly",
    "startDate": "2024-12-01T00:00:00.000Z",
    "endDate": "2025-02-01T00:00:00.000Z",
    "isActive": true,
    "lastPaymentDate": "2024-12-01T00:00:00.000Z",
    "nextPaymentDate": "2025-02-01T00:00:00.000Z",
    "notes": "Active member",
    "createdAt": "2024-11-01T00:00:00.000Z",
    "updatedAt": "2024-12-01T00:00:00.000Z"
  },
  {
    "id": "member13",
    "name": "Christopher White",
    "phone": "9876543222",
    "email": "christopher.white@example.com",
    "avatarUrl": null,
    "membershipType": "quarterly",
    "startDate": "2024-11-01T00:00:00.000Z",
    "endDate": "2025-05-01T00:00:00.000Z",
    "isActive": true,
    "lastPaymentDate": "2024-11-01T00:00:00.000Z",
    "nextPaymentDate": "2025-05-01T00:00:00.000Z",
    "notes": "Long-term active member",
    "createdAt": "2024-10-01T00:00:00.000Z",
    "updatedAt": "2024-11-01T00:00:00.000Z"
  },
  {
    "id": "member14",
    "name": "Amanda Harris",
    "phone": "9876543223",
    "email": "amanda.harris@example.com",
    "avatarUrl": null,
    "membershipType": "yearly",
    "startDate": "2024-06-01T00:00:00.000Z",
    "endDate": "2025-06-01T00:00:00.000Z",
    "isActive": true,
    "lastPaymentDate": "2024-06-01T00:00:00.000Z",
    "nextPaymentDate": "2025-06-01T00:00:00.000Z",
    "notes": "Yearly active membership",
    "createdAt": "2024-05-01T00:00:00.000Z",
    "updatedAt": "2024-06-01T00:00:00.000Z"
  },
  {
    "id": "member15",
    "name": "Daniel Clark",
    "phone": "9876543224",
    "email": "daniel.clark@example.com",
    "avatarUrl": null,
    "membershipType": "monthly",
    "startDate": "2024-12-12T00:00:00.000Z",
    "endDate": "2024-12-19T00:00:00.000Z",
    "isActive": true,
    "lastPaymentDate": "2024-12-12T00:00:00.000Z",
    "nextPaymentDate": "2024-12-19T00:00:00.000Z",
    "notes": "Expires in 3 days",
    "createdAt": "2024-11-12T00:00:00.000Z",
    "updatedAt": "2024-12-12T00:00:00.000Z"
  }
]
